Metadata-Version: 2.4
Name: sqlbot
Version: 2.0.0
Summary: SQLBot - Database Query Bot with AI-powered natural language processing
Author: SQLBot Team
License-Expression: MIT
Project-URL: Homepage, https://github.com/AnthusAI/SQLBot
Project-URL: Repository, https://github.com/AnthusAI/SQLBot.git
Project-URL: Issues, https://github.com/AnthusAI/SQLBot/issues
Keywords: database,dbt,ai,repl,sql,natural-language
Classifier: Development Status :: 3 - Alpha
Classifier: Intended Audience :: Developers
Classifier: Programming Language :: Python :: 3
Classifier: Programming Language :: Python :: 3.8
Classifier: Programming Language :: Python :: 3.9
Classifier: Programming Language :: Python :: 3.10
Classifier: Programming Language :: Python :: 3.11
Classifier: Topic :: Database
Classifier: Topic :: Scientific/Engineering :: Artificial Intelligence
Requires-Python: >=3.8
License-File: LICENSE
Requires-Dist: dbt-core>=1.6.0
Requires-Dist: rich>=13.0.0
Requires-Dist: langchain>=0.3.27
Requires-Dist: langchain-openai>=0.3.32
Requires-Dist: python-dotenv>=1.0.0
Requires-Dist: textual>=0.47.0
Requires-Dist: dotyaml>=0.1.0
Requires-Dist: pandas>=1.5.0
Requires-Dist: openpyxl>=3.0.0
Requires-Dist: pyarrow>=10.0.0
Provides-Extra: sqlserver
Requires-Dist: dbt-sqlserver>=1.6.0; extra == "sqlserver"
Requires-Dist: pyodbc>=4.0.0; extra == "sqlserver"
Provides-Extra: sqlite
Requires-Dist: dbt-sqlite>=1.6.0; extra == "sqlite"
Provides-Extra: dev
Requires-Dist: pytest>=7.0.0; extra == "dev"
Requires-Dist: pytest-bdd>=7.0.0; extra == "dev"
Requires-Dist: pytest-cov>=4.0.0; extra == "dev"
Requires-Dist: pytest-watch>=4.2.0; extra == "dev"
Requires-Dist: black>=23.0.0; extra == "dev"
Requires-Dist: flake8>=6.0.0; extra == "dev"
Requires-Dist: mypy>=1.0.0; extra == "dev"
Dynamic: license-file
